LICENSE
README.md
setup.cfg
setup.py
jobject/__init__.py
jobject/__main__.py
jobject.egg-info/PKG-INFO
jobject.egg-info/SOURCES.txt
jobject.egg-info/dependency_links.txt
jobject.egg-info/top_level.txt
jobject.egg-info/zip-safe