Metadata-Version: 2.1
Name: jobject
Version: 1.0.1
Summary: jobject: A dictionary replacement that gives additional access to data using C struct notation, just like JavaScript Objects
Home-page: https://github.com/ouroboroscoding/jobject
Author: Chris Nasr - Ouroboros Coding Inc.
Author-email: chris@ouroboroscoding.com
License: MIT
Project-URL: Source, https://github.com/ouroboroscoding/jobject
Project-URL: Tracker, https://github.com/ouroboroscoding/jobject/issues
Keywords: javascript,object,struct
Platform: UNKNOWN
Requires-Python: >=3.10
License-File: LICENSE
